README.rst
setup.cfg
setup.py
demo/polls/__init__.py
demo/polls/admin.py
demo/polls/models.py
demo/polls/tests.py
demo/polls/urls.py
demo/polls/views.py
django_related_choice_field.egg-info/PKG-INFO
django_related_choice_field.egg-info/SOURCES.txt
django_related_choice_field.egg-info/dependency_links.txt
django_related_choice_field.egg-info/not-zip-safe
django_related_choice_field.egg-info/requires.txt
django_related_choice_field.egg-info/top_level.txt
related_choice_field/__init__.py
related_choice_field/fields.py